{"2a6cwmHiApbZkP3ihR6BCg==":"ascend_logo3-96x24.png","l5A1LSGrwrEl0PVMLEybig==":"picture1-438x402.png","zUxfmSEhlj5eYG+drQwByg==":"pic1-613x465.png","qV7Wfpa353LAmiTTCHpECA==":"mbr-1920x1280.jpg","8gmvAc5rIQ8iWINvk2Bq9Q==":"mbr-1-1920x1280.jpg","KpzCWtDnzEenF2Y/wn6oKw==":"mbr-1920x1920.png","u+qu4coPMtxSSkk5InL8OA==":"mbr-2-1920x1280.jpg","tic/iEjquJMa1n2a3YOvIQ==":"mbr-3-1920x1280.jpg","7EERhhsp/uH3aoexx9KZcA==":"mbr-4-1920x1280.jpg","PxuvXQtWuu/XB1wlLnNQ6w==":"mbr-5-1920x1280.jpg","w9P+06Q4Gr3CHKq2jINRZg==":"mbr-1046x1280.jpg","ZiyCANxg9tebLX3rDr/4tg==":"mbr-6-1920x1280.jpg","5D7Xk2Iw0fSb+DRUk0blPw==":"mbr-7-1920x1280.jpg","2arRffhhUbcZzqRjH2H5dg==":"mbr-8-1920x1280.jpg","KsACg2m7xyarlun6OI/hPA==":"mbr-9-1920x1280.jpg","mHORW0ykdG8H6CquiAAlBA==":"background4.jpg","BqJl3MzCfCvwj5SzuUWAPA==":"initial_report-697x906.jpg","0rLFbOA1Ey3yCALinitAUg==":"mbr-10-1920x1280.jpg","Qz/biQuRmC1x10HXw993OA==":"quarter_report-624x897.jpg","+psvFl4doIVhx+9nlVMsEg==":"letter_report-696x901.jpg","28FVctHAoA8ssCQlbdIFtA==":"flier_logo-384x653.png","vWdktQRCViBkKBNfhCW5FA==":"ascend_logo-56x25.png","1qTIgaE40FIS/pVP5Z+TEg==":"home_graph-800x735.jpg","nD4gP+cH8uv5dKB1d3rS1g==":"mbr-11-1920x1280.jpg","QK5tibjzCGiv+hFH8Qx1qQ==":"ascend-logo-128x57.png","us+1M0kXUHwjNiAjWUXjlQ==":"mbr-806x537.jpg","+VYZtPUHhWzDoMDyuGmxBQ==":"fig1_program_features-1836x918.png","A63zu1BJvOzCzpe9QCBxew==":"fig2_implementation_sequence-1266x1809.png","DEq9Ye4iW5blKPh+r5j8wA==":"mbr-806x1043.png","Azi3j437LRFLTopo/jq29A==":"mbr-806x806.png","G9mQwczLydkrMHxXS/zOvA==":"mbr-12-1920x1280.jpg","Iprt9grJ6cEqDRHDlXLz7w==":"mbr-1920x1238.jpg","27KfFxRo6tvJYsggvdZoUA==":"cdc-768x576.jpg","yXcAMr14yvNjzWEjNQ2yow==":"qio-394x128.png","+ec+U5thuABTmLIOLjN43A==":"ahrq-376x375.png","IrNgOKuxH4gBQlNoE4qZdg==":"ahrq-1-376x375.png","VOvqVM+/CTzLwbXc/KzAGQ==":"ahrq-2-376x375.png","HNrRMhvvo2CjJiEdKQl7fw==":"rep3-663x924.jpg","p68ukG1Sq+aXjktNaq7h+A==":"letter_report-696x901.jpeg","NyN7LerXYyec+yF0W5DzZA==":"rep3-663x924.jpeg"}